{
  "\"Goldstein Jenőné\" Kramer": {
    "count": 3,
    "docs": [
      [
        "Egyenloseg_1938_1",
        "323"
      ],
      [
        "Egyenloseg_1938_2",
        "128"
      ],
      [
        "PestiHirlap_1930_02",
        "249"
      ]
    ]
  },
  "\"Goldstein Jenőné\" Krámer": {
    "count": 3,
    "docs": [
      [
        "Egyenloseg_1938_1",
        "323"
      ],
      [
        "Egyenloseg_1938_2",
        "128"
      ],
      [
        "PestiHirlap_1930_02",
        "249"
      ]
    ]
  },
  "\"Goldstein Jenőné\" Lea": {
    "count": 2,
    "docs": [
      [
        "MagyarKozlony_1946_Hivatalos_188-298",
        "309"
      ],
      [
        "Ujsag_1930_01",
        "411"
      ]
    ]
  },
  "\"Goldstein Jenő\" Kramer 1936": {
    "count": 1,
    "docs": [
      [
        "Nyirvidek_1936_07",
        "33"
      ]
    ]
  },
  "\"Goldstein Jenő\" Lea": {
    "count": 15,
    "docs": [
      [
        "AzEst_1915_10",
        "186"
      ],
      [
        "AzEst_1915_10",
        "192"
      ],
      [
        "BacsMegyeiNaplo_1931_03",
        "50"
      ],
      [
        "BacsMegyeiNaplo_1937_07",
        "405"
      ],
      [
        "BudapestiKozlony_1944_09",
        "48"
      ],
      [
        "FovarosiKozlony_1911_5",
        "791"
      ],
      [
        "MagyarKozlony_1946_Hivatalos_188-298",
        "309"
      ],
      [
        "Szamos_1924-3",
        "414"
      ],
      [
        "Trencsen_39425_KatolikusGimnazium_39451_1893",
        "60"
      ],
      [
        "Trencsen_39425_KatolikusGimnazium_39453_1895",
        "56"
      ],
      [
        "UjKelet_1927_01",
        "198"
      ],
      [
        "UjKelet_1949_12",
        "146"
      ],
      [
        "UjKelet_1949_12",
        "86"
      ],
      [
        "UjKelet_1950_08",
        "6"
      ],
      [
        "UjKelet_1970_04",
        "204"
      ]
    ]
  },
  "\"Krámer Lea\"": {
    "count": 3,
    "docs": [
      [
        "CurierulNational_1996_07",
        "287"
      ],
      [
        "GrazerVolksblatt_1908_12",
        "475"
      ],
      [
        "PravdaBratislava_OSA_1963_07",
        "79"
      ]
    ]
  },
  "\"Kramer Lea\"": {
    "count": 3,
    "docs": [
      [
        "CurierulNational_1996_07",
        "287"
      ],
      [
        "GrazerVolksblatt_1908_12",
        "475"
      ],
      [
        "PravdaBratislava_OSA_1963_07",
        "79"
      ]
    ]
  },
  "\"Goldstein Jenő\" Vajdahunyad": {
    "count": 10,
    "docs": [
      [
        "Ellenzek_1940_11",
        "69"
      ],
      [
        "MagyarKereskedokLapja_1910_07-12",
        "449"
      ],
      [
        "PestiNaplo_1906_03",
        "701"
      ],
      [
        "PestiNaplo_1908_05",
        "815"
      ],
      [
        "PestiNaplo_1908_12",
        "288"
      ],
      [
        "TypographiaBetu_1908",
        "339"
      ],
      [
        "TypographiaBetu_1909",
        "176"
      ],
      [
        "TypographiaBetu_1909",
        "275"
      ],
      [
        "TypographiaBetu_1909",
        "52"
      ],
      [
        "TypographiaBetu_1909",
        "62"
      ]
    ]
  },
  "\"Goldstein Jenő\" Tel-Aviv": {
    "count": 27,
    "docs": [
      [
        "MagyarNemzet_1992_11",
        "456"
      ],
      [
        "UjKelet_1949_12",
        "146"
      ],
      [
        "UjKelet_1949_12",
        "24"
      ],
      [
        "UjKelet_1949_12",
        "48"
      ],
      [
        "UjKelet_1949_12",
        "86"
      ],
      [
        "UjKelet_1950_07",
        "34"
      ],
      [
        "UjKelet_1950_08",
        "6"
      ],
      [
        "UjKelet_1955_06",
        "142"
      ],
      [
        "UjKelet_1958_10",
        "154"
      ],
      [
        "UjKelet_1958_12",
        "57"
      ],
      [
        "UjKelet_1961_11",
        "38"
      ],
      [
        "UjKelet_1964_11",
        "102"
      ],
      [
        "UjKelet_1964_12",
        "220"
      ],
      [
        "UjKelet_1965_12",
        "246"
      ],
      [
        "UjKelet_1966_10",
        "212"
      ],
      [
        "UjKelet_1966_11",
        "86"
      ],
      [
        "UjKelet_1966_12",
        "186"
      ],
      [
        "UjKelet_1970_04",
        "204"
      ],
      [
        "UjKelet_1970_05",
        "150"
      ],
      [
        "UjKelet_1972_05",
        "168"
      ],
      [
        "UjKelet_1972_08",
        "158"
      ],
      [
        "UjKelet_1973_03",
        "156"
      ],
      [
        "UjKelet_1974_03",
        "142"
      ],
      [
        "UjKelet_1975_03",
        "134"
      ],
      [
        "UjKelet_1976_05",
        "31"
      ],
      [
        "UjKelet_1977_03",
        "222"
      ],
      [
        "UjKelet_1977_03",
        "39"
      ]
    ]
  },
  "\"Goldstein Jenő\" Haifa": {
    "count": 24,
    "docs": [
      [
        "MagyarNemzet_1992_11",
        "456"
      ],
      [
        "UjKelet_1949_12",
        "146"
      ],
      [
        "UjKelet_1949_12",
        "24"
      ],
      [
        "UjKelet_1949_12",
        "48"
      ],
      [
        "UjKelet_1949_12",
        "86"
      ],
      [
        "UjKelet_1950_07",
        "34"
      ],
      [
        "UjKelet_1950_08",
        "6"
      ],
      [
        "UjKelet_1958_10",
        "154"
      ],
      [
        "UjKelet_1958_12",
        "57"
      ],
      [
        "UjKelet_1961_11",
        "38"
      ],
      [
        "UjKelet_1964_11",
        "102"
      ],
      [
        "UjKelet_1964_12",
        "220"
      ],
      [
        "UjKelet_1965_12",
        "246"
      ],
      [
        "UjKelet_1966_10",
        "212"
      ],
      [
        "UjKelet_1966_11",
        "86"
      ],
      [
        "UjKelet_1966_12",
        "186"
      ],
      [
        "UjKelet_1970_04",
        "204"
      ],
      [
        "UjKelet_1970_05",
        "150"
      ],
      [
        "UjKelet_1972_05",
        "168"
      ],
      [
        "UjKelet_1973_03",
        "156"
      ],
      [
        "UjKelet_1975_03",
        "134"
      ],
      [
        "UjKelet_1976_05",
        "31"
      ],
      [
        "UjKelet_1977_03",
        "222"
      ],
      [
        "UjKelet_1977_03",
        "39"
      ]
    ]
  },
  "\"Kramer Zsigmond\" Lea": {
    "count": 3,
    "docs": [
      [
        "BudapestiHirlap_1896_04",
        "286"
      ],
      [
        "MagyarLloyd_1897_01-06",
        "119"
      ],
      [
        "PestiHirlap_1928_05-2",
        "46"
      ]
    ]
  },
  "Krámer Zsigmond Lea": {
    "count": 251,
    "docs": [
      [
        "AHon_1876_01",
        "116"
      ],
      [
        "AHon_1881_04",
        "114"
      ],
      [
        "AHon_1882_03",
        "88"
      ],
      [
        "AMaiNap_1927_01-03",
        "272"
      ],
      [
        "ANep_1922_05",
        "93"
      ],
      [
        "AmerikaiMagyarNepszava_1927_12",
        "91"
      ],
      [
        "AmerikaiMagyarNepszava_1927_12",
        "92"
      ],
      [
        "AmerikaiMagyarNepszava_1929_01",
        "121"
      ],
      [
        "AzUjsag_1904-03_2",
        "195"
      ],
      [
        "AzUjsag_1907_01-1",
        "163"
      ],
      [
        "AzUjsag_1911-02_1",
        "164"
      ],
      [
        "AzUjsag_1912-02_2",
        "346"
      ],
      [
        "AzUjsag_1912-03_1",
        "12"
      ],
      [
        "AzUjsag_1912-09_1",
        "331"
      ],
      [
        "AzUjsag_1914-11",
        "333"
      ],
      [
        "AzUjsag_1914-11",
        "39"
      ],
      [
        "AzUjsag_1914-12",
        "145"
      ],
      [
        "AzUjsag_1915-03",
        "157"
      ],
      [
        "BPLAKCIMJEGYZEK_03_1883-1884",
        "223"
      ],
      [
        "BPLAKCIMJEGYZEK_05_1888",
        "226"
      ],
      [
        "BPLAKCIMJEGYZEK_06_1890",
        "464"
      ],
      [
        "BPLAKCIMJEGYZEK_07_1891-1892",
        "449"
      ],
      [
        "BPLAKCIMJEGYZEK_25_1913",
        "595"
      ],
      [
        "BPLAKCIMJEGYZEK_28_1922-1923",
        "624"
      ],
      [
        "BPLAKCIMJEGYZEK_28_1922-1923",
        "704"
      ],
      [
        "BPLAKCIMJEGYZEK_29_1928",
        "689"
      ],
      [
        "BacsMegyeiNaplo_1922_11",
        "183"
      ],
      [
        "BacsMegyeiNaplo_1927_04",
        "123"
      ],
      [
        "BacsMegyeiNaplo_1930_07",
        "315"
      ],
      [
        "BudapestiHirlap_1896_04",
        "286"
      ],
      [
        "BudapestiHirlap_1896_07",
        "119"
      ],
      [
        "BudapestiHirlap_1906_02",
        "294"
      ],
      [
        "BudapestiHirlap_1914_01",
        "829"
      ],
      [
        "BudapestiHirlap_1914_02",
        "16"
      ],
      [
        "BudapestiKozlony_1871_04",
        "446"
      ],
      [
        "BudapestiKozlony_1926_09_ertesito",
        "63"
      ],
      [
        "BudapestiKozlony_1936_06",
        "73"
      ],
      [
        "BudapestiNaplo_1900_02",
        "424"
      ],
      [
        "Crisana_1963_07-09",
        "24"
      ],
      [
        "CurlisteVonAbbazia_1905-1",
        "319"
      ],
      [
        "CuvantulLiber_2010_09",
        "133"
      ],
      [
        "DeliHirlapTemesvar_1940-2",
        "301"
      ],
      [
        "DieZeit_1906_05",
        "528"
      ],
      [
        "Egyenloseg_1893_2",
        "444"
      ],
      [
        "Egyenloseg_1915_2",
        "260"
      ],
      [
        "Egyenloseg_1916_1",
        "589"
      ],
      [
        "Egyenloseg_1917_2",
        "440"
      ],
      [
        "Egyenloseg_1924",
        "64"
      ],
      [
        "Egyenloseg_1924_1",
        "14"
      ],
      [
        "Egyenloseg_1924_1",
        "378"
      ],
      [
        "Egyenloseg_1929_30_1",
        "327"
      ],
      [
        "Egyenloseg_1933_2",
        "369"
      ],
      [
        "Egyenloseg_1935_1",
        "365"
      ],
      [
        "Egyenloseg_1937_1",
        "46"
      ],
      [
        "EgyetertesMagyarUjsag_1885_03",
        "115"
      ],
      [
        "Ellenor_1881_12",
        "71"
      ],
      [
        "Ellenzek_1885-2",
        "168"
      ],
      [
        "Ellenzek_1943_12",
        "103"
      ],
      [
        "Ellenzek_1943_12",
        "136"
      ],
      [
        "EloreUSA_1913_12",
        "171"
      ],
      [
        "EloreUSA_1915_04",
        "68"
      ],
      [
        "EloreUSA_1917_08",
        "58"
      ],
      [
        "FovarosiKozlony_1913_2",
        "948"
      ],
      [
        "FrissUjsag_1903_09",
        "16"
      ],
      [
        "FrissUjsag_1904_09",
        "73"
      ],
      [
        "FrissUjsag_1909_06",
        "80"
      ],
      [
        "FrissUjsag_1909_07",
        "34"
      ],
      [
        "FrissUjsag_1909_08",
        "118"
      ],
      [
        "FrissUjsag_1909_09",
        "3"
      ],
      [
        "FrissUjsag_1909_11",
        "156"
      ],
      [
        "FrissUjsag_1910_07",
        "128"
      ],
      [
        "FrissUjsag_1910_07",
        "38"
      ],
      [
        "FrissUjsag_1911_05",
        "144"
      ],
      [
        "FrissUjsag_1911_08",
        "75"
      ],
      [
        "FrissUjsag_1911_11",
        "7"
      ],
      [
        "FrissUjsag_1912_01",
        "181"
      ],
      [
        "FrissUjsag_1912_01",
        "28"
      ],
      [
        "FrissUjsag_1912_01",
        "39"
      ],
      [
        "FrissUjsag_1912_02",
        "152"
      ],
      [
        "FrissUjsag_1912_05",
        "6"
      ],
      [
        "FrissUjsag_1913_03",
        "83"
      ],
      [
        "FrissUjsag_1914_06",
        "73"
      ],
      [
        "FrissUjsag_1915_05",
        "108"
      ],
      [
        "FrissUjsag_1915_09",
        "162"
      ],
      [
        "FrissUjsag_1915_10",
        "124"
      ],
      [
        "FrissUjsag_1916_07",
        "158"
      ],
      [
        "FrissUjsag_1916_11",
        "189"
      ],
      [
        "FrissUjsag_1916_11",
        "76"
      ],
      [
        "FrissUjsag_1916_12",
        "173"
      ],
      [
        "FrissUjsag_1917_07",
        "123"
      ],
      [
        "FrissUjsag_1917_09",
        "62"
      ],
      [
        "FrissUjsag_1922_04",
        "107"
      ],
      [
        "FrissUjsag_1923_09",
        "56"
      ],
      [
        "FrissUjsag_1923_12",
        "83"
      ],
      [
        "FrissUjsag_1924_01",
        "31"
      ],
      [
        "FrissUjsag_1924_10",
        "65"
      ],
      [
        "FrissUjsag_1927_11",
        "89"
      ],
      [
        "FrissUjsag_1928_03",
        "41"
      ],
      [
        "FrissUjsag_1928_03",
        "52"
      ],
      [
        "FrissUjsag_1928_05",
        "53"
      ],
      [
        "FrissUjsag_1928_10",
        "41"
      ],
      [
        "FrissUjsag_1933_05",
        "284"
      ],
      [
        "FrissUjsag_1939_05",
        "32"
      ],
      [
        "FrissUjsag_1940_03",
        "251"
      ],
      [
        "FrissUjsag_1942_01",
        "126"
      ],
      [
        "FrissUjsag_1942_04",
        "144"
      ],
      [
        "FuggetlenMagyarorszag1939_1952",
        "187"
      ],
      [
        "Gerichtshalle_1895-1",
        "55"
      ],
      [
        "HiradoPozsony_1930_04-06",
        "202"
      ],
      [
        "IrodalomTortenet_1916",
        "481"
      ],
      [
        "JelenkorPecs_2008_2",
        "492"
      ],
      [
        "JoPajtas_1909",
        "159"
      ],
      [
        "KisUjsag_1938_10",
        "177"
      ],
      [
        "KolozsvariEstilap_1942_07-09",
        "93"
      ],
      [
        "KozlekedesiErtesito_2003",
        "828"
      ],
      [
        "KozlekedesiEsVizugyiErtesito_2001",
        "916"
      ],
      [
        "Kozneveles_1945",
        "81"
      ],
      [
        "Lud_1961-2",
        "10"
      ],
      [
        "MagyarHirlapPozsony_1942_05",
        "33"
      ],
      [
        "MagyarHirlap_1969_07",
        "338"
      ],
      [
        "MagyarHirlap_2008_06",
        "98"
      ],
      [
        "MagyarJovo_1945_07",
        "108"
      ],
      [
        "MagyarJovo_1945_07",
        "49"
      ],
      [
        "MagyarKereskedokLapja_1914_07-12",
        "154"
      ],
      [
        "MagyarKereskedokLapja_1917_07-12",
        "190"
      ],
      [
        "MagyarKereskedokLapja_1918_07-12",
        "200"
      ],
      [
        "MagyarLanyok_1942-43",
        "547"
      ],
      [
        "MagyarLloyd_1897_01-06",
        "119"
      ],
      [
        "MagyarNemzet_1942_12",
        "235"
      ],
      [
        "MagyarNemzet_1950_10",
        "9"
      ],
      [
        "MagyarNemzet_1951_03",
        "78"
      ],
      [
        "MagyarNemzet_1987_04",
        "191"
      ],
      [
        "MagyarNevtaniDolgozatok_136",
        "48"
      ],
      [
        "MagyarSzinpad_1918",
        "288"
      ],
      [
        "MagyarSzinpad_1920",
        "475"
      ],
      [
        "Magyarorszag_1901_01",
        "125"
      ],
      [
        "Magyarorszag_1907_01",
        "682"
      ],
      [
        "Magyarorszag_1915_08",
        "434"
      ],
      [
        "MagyarsagMilotayPetho_1925_07",
        "583"
      ],
      [
        "MagyarsagMilotayPetho_1927_03",
        "467"
      ],
      [
        "Minerva_1915_01",
        "90"
      ],
      [
        "MiskolciMagyarJovo_1929_01-03",
        "182"
      ],
      [
        "MiskolciReggeliHirlap_1934_05",
        "177"
      ],
      [
        "MohacsEsVideke_1896",
        "218"
      ],
      [
        "MoldvaiMagyarsag_1997",
        "5"
      ],
      [
        "Nemzet_1882_11",
        "7"
      ],
      [
        "Nemzet_1884_12",
        "131"
      ],
      [
        "Nemzet_1887_09",
        "181"
      ],
      [
        "Nemzet_1891_04",
        "145"
      ],
      [
        "Nemzet_1893_02",
        "43"
      ],
      [
        "NemzetiSport_1912_1",
        "76"
      ],
      [
        "NemzetiSport_1929_06",
        "208"
      ],
      [
        "NemzetiSport_1948_08",
        "81"
      ],
      [
        "NemzetiSport_1959_10",
        "61"
      ],
      [
        "NemzetiUjsag_1927_01",
        "362"
      ],
      [
        "Nepszava_1919_04",
        "69"
      ],
      [
        "Nepszava_1943_12",
        "158"
      ],
      [
        "Nepszava_2024_05",
        "239"
      ],
      [
        "NeuigkeitsWeltBlatt_1884_12",
        "26"
      ],
      [
        "OrvosiHetilap_1906_01",
        "241"
      ],
      [
        "OrvosiHetilap_1966_01",
        "11"
      ],
      [
        "PapaiKozlony_1917",
        "3"
      ],
      [
        "PecsiNaplo_1900_12",
        "159"
      ],
      [
        "PestMegyeiHirlap_1975_03",
        "53"
      ],
      [
        "PesterLloyd_1884_08",
        "131"
      ],
      [
        "PesterLloyd_1886_12",
        "170"
      ],
      [
        "PesterLloyd_1890_03",
        "140"
      ],
      [
        "PesterLloyd_1891_05",
        "257"
      ],
      [
        "PesterLloyd_1892_08",
        "196"
      ],
      [
        "PesterLloyd_1895_08",
        "79"
      ],
      [
        "PesterLloyd_1897_12",
        "170"
      ],
      [
        "PesterLloyd_1904_03-2",
        "33"
      ],
      [
        "PesterLloyd_1916_10-1",
        "152"
      ],
      [
        "PesterLloyd_1920_01_1_Reggeli",
        "156"
      ],
      [
        "PestiHirlap_1880_06",
        "55"
      ],
      [
        "PestiHirlap_1882_09",
        "93"
      ],
      [
        "PestiHirlap_1895_03",
        "103"
      ],
      [
        "PestiHirlap_1896_03",
        "34"
      ],
      [
        "PestiHirlap_1899_04",
        "185"
      ],
      [
        "PestiHirlap_1906_02-1",
        "412"
      ],
      [
        "PestiHirlap_1906_04-1",
        "158"
      ],
      [
        "PestiHirlap_1907_01",
        "884"
      ],
      [
        "PestiHirlap_1909_09-2",
        "532"
      ],
      [
        "PestiHirlap_1915_10",
        "634"
      ],
      [
        "PestiHirlap_1916_02",
        "423"
      ],
      [
        "PestiHirlap_1916_04",
        "45"
      ],
      [
        "PestiHirlap_1916_05",
        "614"
      ],
      [
        "PestiHirlap_1917_02",
        "457"
      ],
      [
        "PestiHirlap_1924_08",
        "241"
      ],
      [
        "PestiHirlap_1924_10",
        "525"
      ],
      [
        "PestiHirlap_1926_01",
        "449"
      ],
      [
        "PestiHirlap_1926_01",
        "718"
      ],
      [
        "PestiHirlap_1926_09",
        "375"
      ],
      [
        "PestiHirlap_1927_01",
        "353"
      ],
      [
        "PestiHirlap_1928_03",
        "113"
      ],
      [
        "PestiHirlap_1928_03",
        "348"
      ],
      [
        "PestiHirlap_1928_05-2",
        "46"
      ],
      [
        "PestiHirlap_1928_07-1",
        "49"
      ],
      [
        "PestiHirlap_1929_06",
        "284"
      ],
      [
        "PestiHirlap_1929_12",
        "745"
      ],
      [
        "PestiHirlap_1930_04",
        "22"
      ],
      [
        "PestiHirlap_1931_03",
        "26"
      ],
      [
        "PestiHirlap_1934_01",
        "498"
      ],
      [
        "PestiHirlap_1937_11",
        "221"
      ],
      [
        "PestiHirlap_1942_09",
        "59"
      ],
      [
        "PestiMusor_2004_01",
        "288"
      ],
      [
        "PestiNaplo_1876_08_esti",
        "37"
      ],
      [
        "PestiNaplo_1889_03",
        "21"
      ],
      [
        "PestiNaplo_1892_12_esti",
        "28"
      ],
      [
        "PestiNaplo_1893_11",
        "169"
      ],
      [
        "PestiNaplo_1897_06",
        "344"
      ],
      [
        "PestiNaplo_1902_12",
        "403"
      ],
      [
        "PestiNaplo_1906_02",
        "335"
      ],
      [
        "PestiNaplo_1906_03",
        "662"
      ],
      [
        "PestiNaplo_1923_04",
        "107"
      ],
      [
        "PestiNaplo_1927_01",
        "334"
      ],
      [
        "PestiNaplo_1929_01",
        "289"
      ],
      [
        "PestiNaplo_1936_02",
        "533"
      ],
      [
        "PestiNaplo_1936_03",
        "624"
      ],
      [
        "PestiNaplo_1937_02",
        "15"
      ],
      [
        "PoruncaVremii_1938_10",
        "98"
      ],
      [
        "PragaiMagyarHirlap_1936_07",
        "241"
      ],
      [
        "ReggeliUjsagUjvidek_1944_03-04",
        "40"
      ],
      [
        "RudePravo_OSA_1982_05",
        "183"
      ],
      [
        "SomogyMegyeiHirlap_1964_09",
        "45"
      ],
      [
        "Sportul_1985_10",
        "64"
      ],
      [
        "Sportul_1987_09",
        "70"
      ],
      [
        "SteauaRosie_1985_05",
        "57"
      ],
      [
        "SzabadSzoTemesvar_1958-1",
        "135"
      ],
      [
        "Szamos_1928-2",
        "220"
      ],
      [
        "SzekelyfoldMarosvasarhely_1931",
        "16"
      ],
      [
        "TisztiCimtar_1893",
        "258"
      ],
      [
        "TisztiCimtar_1916",
        "606"
      ],
      [
        "TisztiCimtar_1937",
        "148"
      ],
      [
        "UjKelet_1921_04",
        "102"
      ],
      [
        "UjKelet_1924_05",
        "159"
      ],
      [
        "UjKelet_1928_05",
        "78"
      ],
      [
        "UjKelet_1930_01",
        "157"
      ],
      [
        "UjKelet_1961_10",
        "75"
      ],
      [
        "Ujsag_1928_03",
        "351"
      ],
      [
        "Ujsag_1930_01",
        "30"
      ],
      [
        "Ujsag_1930_02",
        "158"
      ],
      [
        "Ujsag_1932_02",
        "180"
      ],
      [
        "Ujsag_1933_12",
        "133"
      ],
      [
        "Ujsag_1935_06",
        "324"
      ],
      [
        "VasarnapiUjsag_1871",
        "153"
      ],
      [
        "Vilag_1917_10",
        "332"
      ],
      [
        "VilagossagRomaniai_1945",
        "959"
      ],
      [
        "Virradat1918_1921_01-03",
        "193"
      ],
      [
        "ZsidoAnyag_UjElet_1969",
        "123"
      ],
      [
        "ZsidoSzemle_1927",
        "47"
      ]
    ]
  },
  "Kramer Lea Majoros": {
    "count": 30,
    "docs": [
      [
        "AzUjsag_1907_01-1",
        "163"
      ],
      [
        "BacsMegyeiNaplo_1931_09",
        "34"
      ],
      [
        "BacsMegyeiNaplo_1932_11",
        "304"
      ],
      [
        "DasVaterland_1872_03",
        "38"
      ],
      [
        "DiePresse_1894_08",
        "242"
      ],
      [
        "EgyetertesMagyarUjsag_1884_08",
        "46"
      ],
      [
        "EgyetertesMagyarUjsag_1885_05",
        "234"
      ],
      [
        "FrissUjsag_1910_07",
        "128"
      ],
      [
        "FrissUjsag_1928_03",
        "251"
      ],
      [
        "Fuggetlenseg_1940_12",
        "220"
      ],
      [
        "HevesVarmegyeHivatalosLapja_1879",
        "38"
      ],
      [
        "JelenkorPecs_2008_2",
        "492"
      ],
      [
        "KozlekedesiEsVizugyiErtesito_2001",
        "916"
      ],
      [
        "MagyarNemzet_1951_01",
        "27"
      ],
      [
        "MiskolciMagyarJovo_1929_01-03",
        "182"
      ],
      [
        "NarodnaObroda_1945_11",
        "84"
      ],
      [
        "NemzetiSport_1966_08",
        "90"
      ],
      [
        "NemzetiUjsag_1940_12",
        "278"
      ],
      [
        "Nyirvidek_1934_11",
        "84"
      ],
      [
        "PesterLloyd_1865_03",
        "114"
      ],
      [
        "PestiHirlap_1893_10",
        "115"
      ],
      [
        "PestiHirlap_1928_05-2",
        "46"
      ],
      [
        "PestiHirlap_1943_07",
        "77"
      ],
      [
        "PestiNaplo_1894_03",
        "198"
      ],
      [
        "PestiNaplo_1931_02",
        "407"
      ],
      [
        "ReggeliUjsagUjvidek_1938_05-06",
        "675"
      ],
      [
        "SlovenskyVychod_1935_04",
        "100"
      ],
      [
        "SlovenskyVychod_1937_08_Novosti",
        "114"
      ],
      [
        "TelegrafPraga_1994_09",
        "463"
      ],
      [
        "VorarlbergerLandesZeitung_1866_04",
        "50"
      ]
    ]
  },
  "Goldstein Krámer eljegyzés": {
    "count": 72,
    "docs": [
      [
        "AReggelKomarom_1931_07",
        "58"
      ],
      [
        "AzEst_1919_02",
        "46"
      ],
      [
        "BME_Boripar_1895",
        "72"
      ],
      [
        "BacsMegyeiNaplo_1930_10",
        "560"
      ],
      [
        "BacsMegyeiNaplo_1933_02",
        "459"
      ],
      [
        "BudapestiHirlap_1898_02",
        "142"
      ],
      [
        "Egyenloseg_1905_2",
        "582"
      ],
      [
        "Egyenloseg_1919",
        "97"
      ],
      [
        "Egyenloseg_1923_1",
        "197"
      ],
      [
        "Egyenloseg_1923_1",
        "307"
      ],
      [
        "Egyenloseg_1924",
        "100"
      ],
      [
        "Egyenloseg_1924",
        "156"
      ],
      [
        "Egyenloseg_1924",
        "582"
      ],
      [
        "Egyenloseg_1924",
        "80"
      ],
      [
        "Egyenloseg_1924_1",
        "114"
      ],
      [
        "Egyenloseg_1924_1",
        "134"
      ],
      [
        "Egyenloseg_1924_1",
        "190"
      ],
      [
        "Egyenloseg_1924_2",
        "346"
      ],
      [
        "Egyenloseg_1925_1",
        "234"
      ],
      [
        "Egyenloseg_1925_2",
        "78"
      ],
      [
        "Egyenloseg_1928_29_1",
        "438"
      ],
      [
        "EgyetertesMagyarUjsag_1882_02",
        "241"
      ],
      [
        "ErdelyiHirlapArad_1928_02",
        "48"
      ],
      [
        "Kaposvar_1902",
        "631"
      ],
      [
        "KassaiNaplo_1923_12",
        "92"
      ],
      [
        "KassaiUjsag_1927_04",
        "253"
      ],
      [
        "KassaiUjsag_1929_10",
        "265"
      ],
      [
        "LosoncEsVideke_1900",
        "17"
      ],
      [
        "Maganalkalmazott_1911",
        "29"
      ],
      [
        "Maganalkalmazott_1914",
        "49"
      ],
      [
        "MagyarJovo_1945_06",
        "55"
      ],
      [
        "MiskolciNaplo_1904_04",
        "19"
      ],
      [
        "MohacsEsVideke_1896",
        "229"
      ],
      [
        "MohacsEsVideke_1899",
        "42"
      ],
      [
        "NagybanyaEsVideke_1908",
        "68"
      ],
      [
        "Nemzet_1882_09",
        "33"
      ],
      [
        "Nemzet_1884_12",
        "60"
      ],
      [
        "Nyirvidek_1910_01-06",
        "64"
      ],
      [
        "Nyirvidek_1922_03",
        "64"
      ],
      [
        "PestiHirlap_1892_11",
        "9"
      ],
      [
        "PestiHirlap_1897_06",
        "432"
      ],
      [
        "PestiHirlap_1909_12-2",
        "386"
      ],
      [
        "PestiHirlap_1910_11-1",
        "235"
      ],
      [
        "PestiNaplo_1871_08",
        "56"
      ],
      [
        "PestiNaplo_1885_11",
        "115"
      ],
      [
        "PestiNaplo_1886_01",
        "67"
      ],
      [
        "PestiNaplo_1886_05",
        "127"
      ],
      [
        "PestiNaplo_1887_08_esti",
        "17"
      ],
      [
        "PestiNaplo_1888_09",
        "55"
      ],
      [
        "PestiNaplo_1889_07_esti",
        "1"
      ],
      [
        "PestiNaplo_1892_04_esti",
        "35"
      ],
      [
        "PestiNaplo_1897_01",
        "251"
      ],
      [
        "PestiNaplo_1928_03",
        "226"
      ],
      [
        "PestiNaplo_1928_03",
        "258"
      ],
      [
        "PestiNaplo_1935_01",
        "149"
      ],
      [
        "Somogy_1883",
        "107"
      ],
      [
        "Somogy_1901",
        "14"
      ],
      [
        "SomogyiHirlap1904_1914_04",
        "98"
      ],
      [
        "SoproniNaplo_1907_04",
        "240"
      ],
      [
        "Szamos_1912_03",
        "119"
      ],
      [
        "Szamos_1923-3",
        "256"
      ],
      [
        "Szamos_1926-2",
        "45"
      ],
      [
        "TolnavarmegyeKozerdek_1910",
        "105"
      ],
      [
        "TolnavarmegyeKozerdek_1913",
        "160"
      ],
      [
        "TolnavarmegyeKozerdek_1914",
        "40"
      ],
      [
        "TolnavarmegyeKozerdek_1915",
        "201"
      ],
      [
        "TolnavarmegyeKozerdek_1917",
        "71"
      ],
      [
        "UjKelet_1929_10",
        "114"
      ],
      [
        "UjKelet_1939_11",
        "85"
      ],
      [
        "UjKelet_1966_10",
        "97"
      ],
      [
        "Ung_1905_01-06",
        "4"
      ],
      [
        "ZsidoUjsag_1930",
        "477"
      ]
    ]
  }
}